[1,["ecpdLyjvZBwrvm+cedCcQy","4by9+Fb75IZJzxxRyr1VJS","afbc7XbzdM26n/TT3tymr/","dcgnVDf7VForgmrts7Qr8e","19GH+BdrtEer6TFa+6csIo","ecdXhj0fNP+Z7FhUakzAsL","1a//sjhNlJ6Kp6wRNwN+6v","5cmEkeE01Ad7gfQ6vV31Ul","d3ZA7NYSVPIYLdIR2Yfcc7","a1+Erl/bdHgZnvYHi9WLZ1","58EkqwHqxAyr8A5MBugqss","16j1PpMrxHjJSVokYzyYTP","2aSXCBiChPdqrXGrWBYaTl","c4KabKKSpEtqchXZAxvPVd","d8HsitJHxOYqo801xBk8ev","02delMVqdBD70a/HSD99FK","23Rjmz8V1J4pBtUmwqEZza","a2MjXRFdtLlYQ5ouAFv/+R","6eFmE2EklEWJAHnXJvJgp5","0ce4acT0NNoK3vTRfHLwQR","96RPtTMqNHdKfIPm9ces4S","6ear6AgaFFWIQX4amYZOLD","569Yb/9LtKIp95avO+6DLq","e6YHQMMMNKV54eOlUvantO","f5l+qatPlFFJLBhHEeRELv","70kMtR3gJFzpreH0JHtvME","7fwrABU5xHvJO/dg/+ImAw","9bvaMerUlDyary99mJa6xp","2cSVUoJuJEwLMou0DqtnWi","da1FOggdpP3o6qGkyxfVf/","4fDK1AvipABpPfIGmleBxA","7aqPxytSdKWq0nsVW6Qbqe"],["node","_spriteFrame","_textureSetter","_N$file","_parent","countNode","nameNode","numNode","root","bottomNode","closeBtn","contentView","sheepRankItem","popNode","labelNode","imgNode","data"],["cc.SpriteFrame",["cc.Node",["_name","_objFlags","_opacity","_active","_prefab","_components","_contentSize","_parent","_children","_trs","_color","_anchorPoint"],-1,4,9,5,1,2,7,5,5],["cc.Widget",["_alignFlags","_top","_bottom","_originalHeight","_originalWidth","_left","_right","node"],-4,1],["cc.Sprite",["_sizeMode","_type","_enabled","node","_materials","_spriteFrame"],0,1,3,6],["cc.PrefabInfo",["fileId","root","asset"],2,1,1],["cc.Label",["_string","_fontSize","_lineHeight","_isSystemFontUsed","_N$horizontalAlign","_N$verticalAlign","_N$cacheMode","node","_materials","_N$file"],-4,1,3,6],["cc.Prefab",["_name"],2],["4f1e6q1O4ZIM6jxip+/6cgl",["node","popNode","sheepRankItem","contentView","closeBtn","bottomNode"],3,1,1,1,1,1,1],["cc.BlockInputEvents",["node"],3,1],["cc.Layout",["_resize","_N$layoutType","_N$paddingTop","_N$paddingBottom","_N$spacingY","node","_layoutSize"],-2,1,5],["3fc70swD4FHKLdy7tN3hR6f",["node","imgNode","labelNode","numNode","nameNode","countNode"],3,1,1,1,1,1,1],["29fbe5db7JFWJL2hqkjASq4",["_enabled","node"],2,1],["cc.ScrollView",["horizontal","brake","bounceDuration","_N$horizontalScrollBar","_N$verticalScrollBar","node","_N$content"],-2,1,1],["cc.Mask",["_N$alphaThreshold","node","_materials"],2,1,3]],[[4,0,1,2,2],[1,0,7,5,4,6,9,2],[3,1,0,3,4,5,3],[5,0,1,2,3,4,5,7,8,9,7],[1,0,3,7,5,4,6,9,3],[3,3,4,5,1],[1,0,7,5,4,10,6,9,2],[1,0,7,8,5,4,6,9,2],[2,0,4,3,7,4],[1,0,8,5,4,6,9,2],[1,0,8,4,2],[1,0,7,8,4,2],[2,0,7,2],[8,0,1],[10,0,1,2,3,4,5,1],[3,0,3,4,5,2],[6,0,2],[1,0,1,8,5,4,6,11,9,3],[1,0,2,7,5,4,10,6,3],[1,0,8,5,4,10,6,9,2],[1,0,7,8,5,4,6,2],[1,0,1,7,8,5,4,6,3],[1,0,7,5,4,6,2],[2,0,1,2,3,7,5],[2,0,2,4,3,7,5],[2,0,1,2,7,4],[2,0,5,6,1,4,7,6],[2,0,5,6,1,2,4,3,7,8],[7,0,1,2,3,4,5,1],[4,1,2,1],[9,0,1,2,3,4,5,6,6],[3,2,1,0,3,4,5,4],[11,0,1,2],[12,0,1,2,3,4,5,6,6],[13,0,1,2,2],[5,0,1,2,3,4,5,6,7,8,9,8]],[[[{"name":"Button_Close1","rect":[0,0,69,76],"offset":[0,0],"originalSize":[69,76],"capInsets":[0,0,0,0]}],[0],0,[0],[2],[5]],[[{"name":"rank_item_black","rect":[0,0,19,59],"offset":[0,0],"originalSize":[19,59],"capInsets":[8,20,8,20]}],[0],0,[0],[2],[6]],[[{"name":"rank_text_red","rect":[0,0,71,37],"offset":[0,0],"originalSize":[71,37],"capInsets":[20,10,20,10]}],[0],0,[0],[2],[7]],[[{"name":"rank_header_silver","rect":[0,0,126,59],"offset":[0,0],"originalSize":[126,59],"capInsets":[0,0,0,0]}],[0],0,[0],[2],[8]],[[{"name":"Base_Gen1","rect":[0,0,78,78],"offset":[0,0],"originalSize":[78,78],"capInsets":[35,35,35,35]}],[0],0,[0],[2],[9]],[[{"name":"rank_header_yellow","rect":[0,0,126,59],"offset":[0,0],"originalSize":[126,59],"capInsets":[0,0,0,0]}],[0],0,[0],[2],[10]],[[{"name":"rank_item_yellow","rect":[0,0,19,59],"offset":[0,0],"originalSize":[19,59],"capInsets":[8,20,8,20]}],[0],0,[0],[2],[11]],[[{"name":"rank_item_white","rect":[0,0,19,59],"offset":[0,0],"originalSize":[19,59],"capInsets":[8,20,8,20]}],[0],0,[0],[2],[12]],[[{"name":"Base_Title1","rect":[0,0,52,91],"offset":[0,0],"originalSize":[52,91],"capInsets":[21,36,21,35]}],[0],0,[0],[2],[13]],[[{"name":"default_panel","rect":[0,0,20,20],"offset":[0,0],"originalSize":[20,20],"capInsets":[6,6,6,6]}],[0],0,[0],[2],[14]],[[{"name":"default_sprite_splash","rect":[0,0,2,2],"offset":[0,0],"originalSize":[2,2],"capInsets":[0,0,0,0]}],[0],0,[0],[2],[15]],[[{"name":"rank_text_black","rect":[0,0,37,37],"offset":[0,0],"originalSize":[37,37],"capInsets":[12,12,12,12]}],[0],0,[0],[2],[16]],[[[16,"sheepRankPop"],[9,"sheepRankPop",[-9,-10],[[12,45,-2],[28,-8,-7,-6,-5,-4,-3]],[29,-1,0],[5,750,1334],[375,667,0,0,0,0,1,1,1,1]],[10,"imgNode",[-11,-12,-13,-14,-15,-16,-17,-18,-19,-20],[0,"58ReNyBm5DPal1Q8k9RbII",1,0]],[7,"pop",1,[-23,-24,-25],[[23,21,150,100,1149,-21],[13,-22]],[0,"c6YnGiHpVEY7bfbsiA/ozV",1,0],[5,547,1084],[0,-25,0,0,0,0,1,1,1,1]],[17,"content",512,[-28],[[30,1,2,10,10,10,-26,[5,507,80]],[24,45,844,220,400,-27]],[0,"6a34/QmndIOa5KLHVuHpKD",1,0],[5,507,80],[0,0.5,1],[0,462,0,0,0,0,1,1,1,1]],[10,"labelNode",[-29,-30,-31,-32],[0,"e9R19XGeBHQ6JHGiEddtRz",1,0]],[9,"sheepRankItem",[-40,-41],[[25,4,220,40,-33],[14,-39,-38,-37,-36,-35,-34]],[0,"b3KfdRiBZBT6To3R1/4U40",1,0],[5,500,60],[0,-472,0,0,0,0,1,1,1,1]],[11,"imgNode",6,[-42,-43,-44,-45],[0,"7bm1OuWKdE9JkoAEE7Mzrv",1,0]],[11,"labelNode",6,[-46,-47,-48,-49],[0,"f9pQOTNb5I+YCXVhmHSJpt",1,0]],[18,"mask",128,1,[[15,0,-50,[0],1],[8,45,100,100,-51],[32,false,-52],[13,-53]],[0,"a2JGCLwW9M0Jl04EdA8Tq7",1,0],[4,4278190080],[5,750,1334]],[7,"title-node",3,[-56,-57],[[2,1,0,-54,[8],9],[26,41,107.5,107.5,-39.74200000000002,580,-55]],[0,"67uH4UcQREy7027OIIM/pn",1,0],[5,332,91],[0,536.242,0,0,0,0,1,1,1,1]],[19,"scrollView",[-61],[[31,false,1,0,-58,[39],40],[33,false,0.75,0.23,null,null,-59,4],[27,45,20,20,60,100,240,250,-60]],[0,"2aHCHOexhDpbTK5GoZFygo",1,0],[4,4288256409],[5,507,924],[0,20,0,0,0,0,1,1,1,1]],[7,"sheepRankItem",4,[2,5],[[14,-65,2,5,-64,-63,-62]],[0,"fbuVfK89BP/6JNHZMtGxca",1,0],[5,500,60],[0,-40,0,0,0,0,1,1,1,1]],[20,"content-view",3,[11,6],[[12,45,-66]],[0,"01PDKxAPNA75znIDo1FhFf",1,0],[5,547,1084]],[21,"view",512,11,[4],[[34,0,-67,[38]],[8,45,240,250,-68]],[0,"bfg4ku0YFN0pUbfJ0pZpIq",1,0],[5,507,924]],[22,"bg",3,[[2,1,0,-69,[2],3],[8,45,580,870,-70]],[0,"3brSmwBtlAErpabMGdwkcW",1,0],[5,547,1084]],[1,"close-btn",10,[[15,2,-71,[6],7]],[0,"d4FP+N5R5D16ZWyUNeSeF8",1,0],[5,69,76],[255.913,-16.006,0,0,0,0,1,1,1,1]],[6,"num-label",5,[[3,"8",36,36,false,1,1,-72,[30],31]],[0,"fdOM4wBThNgaEoppv4Uanc",1,0],[4,4278190080],[5,20,36],[-159.509,3.458,0,0,0,0,1,1,1,1]],[1,"name-label",5,[[3,"北京",30,26,false,1,1,-73,[32],33]],[0,"a0Ebqut2FDtY3D6qU4RU1j",1,0],[5,57.5,26],[-47,2.592,0,0,0,0,1,1,1,1]],[1,"count-label",5,[[3,"12066",30,26,false,1,1,-74,[34],35]],[0,"66qz2wZVJEkpMLv2vVx3jM",1,0],[5,87.5,26],[115.284,1.727,0,0,0,0,1,1,1,1]],[1,"num-label",8,[[3,"8",36,36,false,1,1,-75,[49],50]],[0,"451j10h+BIYah3dJyNGREQ",1,0],[5,20,36],[-159.509,3.458,0,0,0,0,1,1,1,1]],[1,"name-label",8,[[3,"北京",30,26,false,1,1,-76,[51],52]],[0,"5e7L/AMqJGQ4ox+9m2Yms6",1,0],[5,57.5,26],[-47,2.592,0,0,0,0,1,1,1,1]],[1,"count-label",8,[[3,"12066",30,26,false,1,1,-77,[53],54]],[0,"a8yU5iKy1DtaR286Vd1tmK",1,0],[5,87.5,26],[115.284,1.727,0,0,0,0,1,1,1,1]],[6,"label",10,[[35,"今日头羊榜",38,50,false,1,1,1,-78,[4],5]],[0,"25E5kSi+BPcbq3L1IYQ7P6",1,0],[4,4278248703],[5,188.94,50],[0,5.788,0,0,0,0,1,1,1,1]],[1,"num-yellow",2,[[5,-79,[10],11]],[0,"6fTumxofNNTrWg0UWJIt54",1,0],[5,126,59],[-173.357,0,0,0,0,0,1,1,1,1]],[4,"num-sliver",false,2,[[5,-80,[12],13]],[0,"bbp1K5nH1Os4vRP8I/u4e9",1,0],[5,126,59],[-173.357,0,0,0,0,0,1,1,1,1]],[4,"num-orange",false,2,[[5,-81,[14],15]],[0,"6cVjv0W/1Pnq/1cIF1y9Z3",1,0],[5,126,59],[-173.357,0,0,0,0,0,1,1,1,1]],[4,"num-blue",false,2,[[5,-82,[16],17]],[0,"92Kc/SJ6NLj7sXiNILKYeU",1,0],[5,126,59],[-173.357,0,0,0,0,0,1,1,1,1]],[4,"num-black",false,2,[[5,-83,[18],19]],[0,"79wRlQk5xP1rH2KRrMTg24",1,0],[5,126,59],[-173.357,0,0,0,0,0,1,1,1,1]],[1,"img-yellow",2,[[2,1,0,-84,[20],21]],[0,"d1GtOHdKJAdJH/9sx5O1Ht",1,0],[5,334,59],[60.859,0,0,0,0,0,1,1,1,1]],[4,"img-white",false,2,[[2,1,0,-85,[22],23]],[0,"3edf85ZkhC1Lpo7P40Vp1b",1,0],[5,334,59],[60.859,0,0,0,0,0,1,1,1,1]],[4,"img-black",false,2,[[2,1,0,-86,[24],25]],[0,"61pY8+/2FO5I1EaHScInm3",1,0],[5,334,59],[60.859,0,0,0,0,0,1,1,1,1]],[1,"text-black",2,[[2,1,0,-87,[26],27]],[0,"beocEh9q9C+ZzGPYFDREGU",1,0],[5,100,37],[-45,1.576,0,0,0,0,1,1,1,1]],[1,"text-sheep-black",2,[[2,1,0,-88,[28],29]],[0,"f2kndmwMhM/IUhW2/hbRTE",1,0],[5,164,37],[135.687,1.576,0,0,0,0,1,1,1,1]],[6,"tag-label",5,[[3,"羊",26,26,false,1,1,-89,[36],37]],[0,"64MGW4JPlDh49ROFYy7leI",1,0],[4,4281322239],[5,24.56,26],[200.492,1.759,0,0,0,0,1,1,1,1]],[1,"num-black",7,[[5,-90,[41],42]],[0,"835L6rQkJGdpoBXc8ZSWJx",1,0],[5,126,59],[-173.357,0,0,0,0,0,1,1,1,1]],[1,"img-black",7,[[2,1,0,-91,[43],44]],[0,"4bX+b+YdVMUao7DTW07ynX",1,0],[5,334,59],[60.859,0,0,0,0,0,1,1,1,1]],[1,"text-red",7,[[2,1,0,-92,[45],46]],[0,"a1GFDwrlRCJ4CVIsrsUCcH",1,0],[5,100,37],[-45,1.576,0,0,0,0,1,1,1,1]],[1,"text-sheep-black",7,[[2,1,0,-93,[47],48]],[0,"59o0jYVM9FnZhOeA+OWK81",1,0],[5,164,37],[135.687,1.576,0,0,0,0,1,1,1,1]],[6,"tag-label",8,[[3,"羊",26,26,false,1,1,-94,[55],56]],[0,"26jiygGkBNJ7F/90/se7Ps",1,0],[4,4281322239],[5,24.56,26],[200.492,1.121,0,0,0,0,1,1,1,1]]],0,[0,8,1,0,0,1,0,9,6,0,10,16,0,11,4,0,12,12,0,13,3,0,0,1,0,-1,9,0,-2,3,0,-1,24,0,-2,25,0,-3,26,0,-4,27,0,-5,28,0,-6,29,0,-7,30,0,-8,31,0,-9,32,0,-10,33,0,0,3,0,0,3,0,-1,15,0,-2,10,0,-3,13,0,0,4,0,0,4,0,-1,12,0,-1,17,0,-2,18,0,-3,19,0,-4,34,0,0,6,0,5,22,0,6,21,0,7,20,0,14,8,0,15,7,0,0,6,0,-1,7,0,-2,8,0,-1,35,0,-2,36,0,-3,37,0,-4,38,0,-1,20,0,-2,21,0,-3,22,0,-4,39,0,0,9,0,0,9,0,0,9,0,0,9,0,0,10,0,0,10,0,-1,23,0,-2,16,0,0,11,0,0,11,0,0,11,0,-1,14,0,5,19,0,6,18,0,7,17,0,0,12,0,0,13,0,0,14,0,0,14,0,0,15,0,0,15,0,0,16,0,0,17,0,0,18,0,0,19,0,0,20,0,0,21,0,0,22,0,0,23,0,0,24,0,0,25,0,0,26,0,0,27,0,0,28,0,0,29,0,0,30,0,0,31,0,0,32,0,0,33,0,0,34,0,0,35,0,0,36,0,0,37,0,0,38,0,0,39,0,16,1,2,4,12,4,4,14,5,4,12,6,4,13,11,4,13,94],[0,0,0,0,0,0,0,0,0,0,0,0,0,0,0,0,0,0,0,0,0,0,0,0,0,0,0,0,0,0,0,0,0,0,0,0,0,0,0,0,0,0,0,0,0,0,0,0,0,0,0,0,0,0,0,0,0],[-1,1,-1,1,-1,3,-1,1,-1,1,-1,1,-1,1,-1,1,-1,1,-1,1,-1,1,-1,1,-1,1,-1,1,-1,1,-1,3,-1,3,-1,3,-1,3,-1,-1,1,-1,1,-1,1,-1,1,-1,1,-1,3,-1,3,-1,3,-1,3],[0,17,0,18,0,1,0,19,0,20,0,21,0,22,0,23,0,24,0,3,0,25,0,26,0,4,0,2,0,2,0,1,0,1,0,1,0,1,0,0,27,0,3,0,4,0,28,0,2,0,1,0,1,0,1,0,1]],[[{"name":"rank_header_black","rect":[0,0,126,59],"offset":[0,0],"originalSize":[126,59],"capInsets":[0,0,0,0]}],[0],0,[0],[2],[29]],[[{"name":"rank_header_orange","rect":[0,0,126,59],"offset":[0,0],"originalSize":[126,59],"capInsets":[0,0,0,0]}],[0],0,[0],[2],[30]],[[{"name":"rank_header_blue","rect":[0,0,126,59],"offset":[0,0],"originalSize":[126,59],"capInsets":[0,0,0,0]}],[0],0,[0],[2],[31]]]]